setup.py
gnscli/__init__.py
gnscli/checker.py
gnscli/client.py
gnscli/config.yaml
gnscli/gnsapi.py
gnscli/settings.py
gnscli/uploader.py
gnscli.egg-info/PKG-INFO
gnscli.egg-info/SOURCES.txt
gnscli.egg-info/dependency_links.txt
gnscli.egg-info/entry_points.txt
gnscli.egg-info/requires.txt
gnscli.egg-info/top_level.txt