Metadata-Version: 1.0
Name: gnscli
Version: 0.7.0-alpha-bcb9f0f
Summary: GNS Command line tool
Home-page: https://github.com/yandex-sysmon/gns-cli
Author: Alexander Kushnarev
Author-email: avkushnarev@gmail.com
License: UNKNOWN
Platform: UNKNOWN
